wxgen/__init__.py
wxgen/aggregator.py
wxgen/climate_model.py
wxgen/database.py
wxgen/downscaler.py
wxgen/driver.py
wxgen/generator.py
wxgen/metric.py
wxgen/output.py
wxgen/plot.py
wxgen/trajectory.py
wxgen/transform.py
wxgen/util.py
wxgen/variable.py
wxgen/version.py
wxgen-0.2.0a1.dist-info/DESCRIPTION.rst
wxgen-0.2.0a1.dist-info/METADATA
wxgen-0.2.0a1.dist-info/RECORD
wxgen-0.2.0a1.dist-info/WHEEL
wxgen-0.2.0a1.dist-info/entry_points.txt
wxgen-0.2.0a1.dist-info/metadata.json
wxgen-0.2.0a1.dist-info/top_level.txt
