Metadata-Version: 2.0
Name: wxgen
Version: 0.2.0a1
Summary: A package for generating arbitrarily long weather time-series
Home-page: https://github.com/metno/wxgen
Author: Thomas Nipen
Author-email: thomas.nipen@met.no
License: LGPL-3
Keywords: meteorology generator stochastic weather
Platform: UNKNOWN
Classifier: Development Status :: 3 - Alpha
Classifier: Intended Audience :: Science/Research
Classifier: Topic :: Scientific/Engineering :: Atmospheric Science
Classifier: Topic :: Scientific/Engineering :: Information Analysis
Classifier: License :: OSI Approved :: GNU Lesser General Public License v3 (LGPLv3)
Classifier: Programming Language :: Python :: 2
Classifier: Programming Language :: Python :: 2.6
Classifier: Programming Language :: Python :: 2.7
Requires-Dist: PyWavelets
Requires-Dist: astropy (==1.3.1)
Requires-Dist: matplotlib (>=1.3,<2)
Requires-Dist: netCDF4
Requires-Dist: numpy (>=1.7)
Requires-Dist: scipy
Provides-Extra: test
Requires-Dist: coverage; extra == 'test'
Requires-Dist: pep8; extra == 'test'
